pytest_docker/__init__.py
pytest_docker/plugin.py
pytest_docker/py.typed
pytest_docker-3.2.5.dist-info/licenses/LICENSE.txt
pytest_docker-3.2.5.dist-info/METADATA
pytest_docker-3.2.5.dist-info/WHEEL
pytest_docker-3.2.5.dist-info/entry_points.txt
pytest_docker-3.2.5.dist-info/top_level.txt
pytest_docker-3.2.5.dist-info/RECORD
