Metadata-Version: 2.4
Name: pytest-docker
Version: 3.2.5
Summary: Simple pytest fixtures for Docker and Docker Compose based tests
Home-page: https://github.com/avast/pytest-docker
Author: Max K., Andre Caron
Author-email: maxim.kovykov@avast.com
License: MIT
Keywords: docker,docker-compose,pytest
Classifier: Programming Language :: Python :: 3
Classifier: Programming Language :: Python :: 3.8
Classifier: Programming Language :: Python :: 3.9
Classifier: Programming Language :: Python :: 3.10
Classifier: Programming Language :: Python :: 3.11
Classifier: Programming Language :: Python :: 3.12
Classifier: Programming Language :: Python :: 3.13
Classifier: License :: OSI Approved :: MIT License
Classifier: Topic :: Utilities
Classifier: Intended Audience :: Developers
Classifier: Operating System :: Unix
Classifier: Operating System :: POSIX
Classifier: Operating System :: Microsoft :: Windows
Requires-Python: >=3.8
License-File: LICENSE.txt
Requires-Dist: pytest<10.0,>=4.0
Requires-Dist: attrs>=19.2.0
Provides-Extra: docker-compose-v1
Requires-Dist: docker-compose<2.0,>=1.27.3; extra == "docker-compose-v1"
Provides-Extra: tests
Requires-Dist: requests<3.0,>=2.22.0; extra == "tests"
Requires-Dist: mypy<2.000,>=0.500; extra == "tests"
Requires-Dist: pytest-pylint<1.0,>=0.14.1; extra == "tests"
Requires-Dist: pytest-pycodestyle<3.0,>=2.0.0; extra == "tests"
Requires-Dist: pytest-mypy<1.0,>=0.10; extra == "tests"
Requires-Dist: types-requests<3.0,>=2.31; extra == "tests"
Requires-Dist: types-setuptools<70.0,>=69.0; extra == "tests"
Dynamic: license-file
